csv_remapper/__init__.py
csv_remapper/__main__.py
csv_remapper/constants.py
csv_remapper/components/__init__.py
csv_remapper/components/cli.py
csv_remapper/components/datatypes.py
csv_remapper/components/decorators.py
csv_remapper/components/delegates.py
csv_remapper/components/dialogs.py
csv_remapper/components/io_handlers.py
csv_remapper/components/models.py
csv_remapper/components/remappers.py
csv_remapper/components/views.py
csv_remapper/components/wizards.py
csv_remapper/resources/Accounts-Icon.png
csv_remapper/resources/__init__.py
csv_remapper/resources/_build_resources.py
csv_remapper/resources/data_editor_ui.py
csv_remapper/resources/data_editor_ui.ui
csv_remapper/resources/main_window_ui.py
csv_remapper/resources/main_window_ui.ui
csv_remapper/resources/template_editor_ui.py
csv_remapper/resources/template_editor_ui.ui
csv_remapper/utils/__init__.py
csv_remapper/utils/build_resources.py
csv_remapper/widgets/__init__.py
csv_remapper/widgets/compare_window.py
csv_remapper/widgets/data_editor.py
csv_remapper/widgets/drag_drop_table.py
csv_remapper/widgets/main_window.py
csv_remapper/widgets/template_editor.py
csv_remapper-1.1.7.dist-info/entry_points.txt
csv_remapper-1.1.7.dist-info/LICENSE
csv_remapper-1.1.7.dist-info/WHEEL
csv_remapper-1.1.7.dist-info/METADATA
csv_remapper-1.1.7.dist-info/RECORD
